deepeye/__init__.py
deepeye/unified_scanpath_decoder/ConvNet.py
deepeye/unified_scanpath_decoder/InceptionTime.py
deepeye/unified_scanpath_decoder/__init__.py
deepeye/unified_scanpath_decoder/backbone.py
deepeye/unified_scanpath_decoder/model_loader.py
deepeye/unified_scanpath_decoder/modules.py
deepeye/unified_scanpath_decoder/position_encoding.py
deepeye/unified_scanpath_decoder/transformer.py
deepeye_models-0.1.0.dist-info/METADATA
deepeye_models-0.1.0.dist-info/WHEEL
deepeye_models-0.1.0.dist-info/top_level.txt
deepeye_models-0.1.0.dist-info/RECORD
