Metadata-Version: 2.1
Name: deepeye-models
Version: 0.1.0
Summary: DeepEye: EEG-based AI Eye-Tracking Models
Author: Radim Urban
Requires-Dist: torch
Requires-Dist: numpy
Requires-Dist: huggingface-hub
